helloworld.py
MrMuralipyautotest-0.0.15.dist-info/METADATA
MrMuralipyautotest-0.0.15.dist-info/WHEEL
MrMuralipyautotest-0.0.15.dist-info/top_level.txt
MrMuralipyautotest-0.0.15.dist-info/RECORD
