Metadata-Version: 2.1
Name: MrMuralipyautotest
Version: 0.0.15
Summary: Say hello
Author: NeuralNine (Florian Dedov)
Author-email: <mail@neuralnine.com>
